{
  "calculator.gaiamobile.org": {
    "origin": "app://calculator.gaiamobile.org",
    "installOrigin": "app://calculator.gaiamobile.org",
    "receipt": null,
    "installTime": 132333986000,
    "manifestURL": "app://calculator.gaiamobile.org/manifest.webapp",
    "appStatus": 3,
    "localId": 1001,
    "basePath": "/system/b2g/webapps",
    "removable": false,
    "name": "Calculator",
    "csp": "",
    "installerAppId": 0,
    "installerIsBrowser": false
  },
  "costcontrol.gaiamobile.org": {
    "origin": "app://costcontrol.gaiamobile.org",
    "installOrigin": "app://costcontrol.gaiamobile.org",
    "receipt": null,
    "installTime": 132333986000,
    "manifestURL": "app://costcontrol.gaiamobile.org/manifest.webapp",
    "appStatus": 3,
    "localId": 1002,
    "basePath": "/system/b2g/webapps",
    "removable": false,
    "name": "Cost Control",
    "csp": "",
    "installerAppId": 0,
    "installerIsBrowser": false
  },
  "clock.gaiamobile.org": {
    "origin": "app://clock.gaiamobile.org",
    "installOrigin": "app://clock.gaiamobile.org",
    "receipt": null,
    "installTime": 132333986000,
    "manifestURL": "app://clock.gaiamobile.org/manifest.webapp",
    "appStatus": 3,
    "localId": 1003,
    "basePath": "/system/b2g/webapps",
    "removable": false,
    "name": "Clock",
    "csp": "",
    "installerAppId": 0,
    "installerIsBrowser": false
  },
  "settings.gaiamobile.org": {
    "origin": "app://settings.gaiamobile.org",
    "installOrigin": "app://settings.gaiamobile.org",
    "receipt": null,
    "installTime": 132333986000,
    "manifestURL": "app://settings.gaiamobile.org/manifest.webapp",
    "appStatus": 3,
    "localId": 1004,
    "basePath": "/system/b2g/webapps",
    "removable": false,
    "name": "Settings",
    "csp": "",
    "installerAppId": 0,
    "installerIsBrowser": false
  },
  "pdfjs.gaiamobile.org": {
    "origin": "app://pdfjs.gaiamobile.org",
    "installOrigin": "app://pdfjs.gaiamobile.org",
    "receipt": null,
    "installTime": 132333986000,
    "manifestURL": "app://pdfjs.gaiamobile.org/manifest.webapp",
    "appStatus": 3,
    "localId": 1005,
    "basePath": "/system/b2g/webapps",
    "removable": false,
    "name": "PDF Viewer",
    "csp": "",
    "installerAppId": 0,
    "installerIsBrowser": false
  },
  "camera.gaiamobile.org": {
    "origin": "app://camera.gaiamobile.org",
    "installOrigin": "app://camera.gaiamobile.org",
    "receipt": null,
    "installTime": 132333986000,
    "manifestURL": "app://camera.gaiamobile.org/manifest.webapp",
    "appStatus": 3,
    "localId": 1006,
    "basePath": "/system/b2g/webapps",
    "removable": false,
    "name": "Camera",
    "csp": "",
    "installerAppId": 0,
    "installerIsBrowser": false
  },
  "system.gaiamobile.org": {
    "origin": "app://system.gaiamobile.org",
    "installOrigin": "app://system.gaiamobile.org",
    "receipt": null,
    "installTime": 132333986000,
    "manifestURL": "app://system.gaiamobile.org/manifest.webapp",
    "appStatus": 3,
    "localId": 1007,
    "basePath": "/system/b2g/webapps",
    "removable": false,
    "name": "System",
    "csp": "",
    "installerAppId": 0,
    "installerIsBrowser": false
  },
  "email.gaiamobile.org": {
    "origin": "app://email.gaiamobile.org",
    "installOrigin": "app://email.gaiamobile.org",
    "receipt": null,
    "installTime": 132333986000,
    "manifestURL": "app://email.gaiamobile.org/manifest.webapp",
    "appStatus": 3,
    "localId": 1008,
    "basePath": "/system/b2g/webapps",
    "removable": false,
    "name": "E-Mail",
    "csp": "",
    "installerAppId": 0,
    "installerIsBrowser": false
  },
  "wallpaper.gaiamobile.org": {
    "origin": "app://wallpaper.gaiamobile.org",
    "installOrigin": "app://wallpaper.gaiamobile.org",
    "receipt": null,
    "installTime": 132333986000,
    "manifestURL": "app://wallpaper.gaiamobile.org/manifest.webapp",
    "appStatus": 3,
    "localId": 1009,
    "basePath": "/system/b2g/webapps",
    "removable": false,
    "name": "Wallpaper",
    "csp": "",
    "installerAppId": 0,
    "installerIsBrowser": false
  },
  "calendar.gaiamobile.org": {
    "origin": "app://calendar.gaiamobile.org",
    "installOrigin": "app://calendar.gaiamobile.org",
    "receipt": null,
    "installTime": 132333986000,
    "manifestURL": "app://calendar.gaiamobile.org/manifest.webapp",
    "appStatus": 3,
    "localId": 1010,
    "basePath": "/system/b2g/webapps",
    "removable": false,
    "name": "Calendar",
    "csp": "",
    "installerAppId": 0,
    "installerIsBrowser": false
  },
  "feedback.gaiamobile.org": {
    "origin": "app://feedback.gaiamobile.org",
    "installOrigin": "app://feedback.gaiamobile.org",
    "receipt": null,
    "installTime": 132333986000,
    "manifestURL": "app://feedback.gaiamobile.org/manifest.webapp",
    "appStatus": 3,
    "localId": 1011,
    "basePath": "/system/b2g/webapps",
    "removable": false,
    "name": "Feedback",
    "csp": "",
    "installerAppId": 0,
    "installerIsBrowser": false
  },
  "sms.gaiamobile.org": {
    "origin": "app://sms.gaiamobile.org",
    "installOrigin": "app://sms.gaiamobile.org",
    "receipt": null,
    "installTime": 132333986000,
    "manifestURL": "app://sms.gaiamobile.org/manifest.webapp",
    "appStatus": 3,
    "localId": 1012,
    "basePath": "/system/b2g/webapps",
    "removable": false,
    "name": "Messages",
    "csp": "",
    "installerAppId": 0,
    "installerIsBrowser": false
  },
  "bluetooth.gaiamobile.org": {
    "origin": "app://bluetooth.gaiamobile.org",
    "installOrigin": "app://bluetooth.gaiamobile.org",
    "receipt": null,
    "installTime": 132333986000,
    "manifestURL": "app://bluetooth.gaiamobile.org/manifest.webapp",
    "appStatus": 3,
    "localId": 1013,
    "basePath": "/system/b2g/webapps",
    "removable": false,
    "name": "Send To Bluetooth Device",
    "csp": "",
    "installerAppId": 0,
    "installerIsBrowser": false
  },
  "keyboard.gaiamobile.org": {
    "origin": "app://keyboard.gaiamobile.org",
    "installOrigin": "app://keyboard.gaiamobile.org",
    "receipt": null,
    "installTime": 132333986000,
    "manifestURL": "app://keyboard.gaiamobile.org/manifest.webapp",
    "appStatus": 3,
    "localId": 1014,
    "basePath": "/system/b2g/webapps",
    "removable": false,
    "name": "Keyboard",
    "csp": "",
    "installerAppId": 0,
    "installerIsBrowser": false
  },
  "gallery.gaiamobile.org": {
    "origin": "app://gallery.gaiamobile.org",
    "installOrigin": "app://gallery.gaiamobile.org",
    "receipt": null,
    "installTime": 132333986000,
    "manifestURL": "app://gallery.gaiamobile.org/manifest.webapp",
    "appStatus": 3,
    "localId": 1015,
    "basePath": "/system/b2g/webapps",
    "removable": false,
    "name": "Gallery",
    "csp": "",
    "installerAppId": 0,
    "installerIsBrowser": false
  },
  "video.gaiamobile.org": {
    "origin": "app://video.gaiamobile.org",
    "installOrigin": "app://video.gaiamobile.org",
    "receipt": null,
    "installTime": 132333986000,
    "manifestURL": "app://video.gaiamobile.org/manifest.webapp",
    "appStatus": 3,
    "localId": 1016,
    "basePath": "/system/b2g/webapps",
    "removable": false,
    "name": "Video",
    "csp": "",
    "installerAppId": 0,
    "installerIsBrowser": false
  },
  "fm.gaiamobile.org": {
    "origin": "app://fm.gaiamobile.org",
    "installOrigin": "app://fm.gaiamobile.org",
    "receipt": null,
    "installTime": 132333986000,
    "manifestURL": "app://fm.gaiamobile.org/manifest.webapp",
    "appStatus": 3,
    "localId": 1017,
    "basePath": "/system/b2g/webapps",
    "removable": false,
    "name": "FM Radio",
    "csp": "",
    "installerAppId": 0,
    "installerIsBrowser": false
  },
  "communications.gaiamobile.org": {
    "origin": "app://communications.gaiamobile.org",
    "installOrigin": "app://communications.gaiamobile.org",
    "receipt": null,
    "installTime": 132333986000,
    "manifestURL": "app://communications.gaiamobile.org/manifest.webapp",
    "appStatus": 3,
    "localId": 1018,
    "basePath": "/system/b2g/webapps",
    "removable": false,
    "name": "Communications",
    "csp": "",
    "installerAppId": 0,
    "installerIsBrowser": false
  },
  "browser.gaiamobile.org": {
    "origin": "app://browser.gaiamobile.org",
    "installOrigin": "app://browser.gaiamobile.org",
    "receipt": null,
    "installTime": 132333986000,
    "manifestURL": "app://browser.gaiamobile.org/manifest.webapp",
    "appStatus": 3,
    "localId": 1019,
    "basePath": "/system/b2g/webapps",
    "removable": false,
    "name": "Browser",
    "csp": "",
    "installerAppId": 0,
    "installerIsBrowser": false
  },
  "homescreen.gaiamobile.org": {
    "origin": "app://homescreen.gaiamobile.org",
    "installOrigin": "app://homescreen.gaiamobile.org",
    "receipt": null,
    "installTime": 132333986000,
    "manifestURL": "app://homescreen.gaiamobile.org/manifest.webapp",
    "appStatus": 3,
    "localId": 1020,
    "basePath": "/system/b2g/webapps",
    "removable": false,
    "name": "Homescreen",
    "csp": "",
    "installerAppId": 0,
    "installerIsBrowser": false
  },
  "music.gaiamobile.org": {
    "origin": "app://music.gaiamobile.org",
    "installOrigin": "app://music.gaiamobile.org",
    "receipt": null,
    "installTime": 132333986000,
    "manifestURL": "app://music.gaiamobile.org/manifest.webapp",
    "appStatus": 3,
    "localId": 1021,
    "basePath": "/system/b2g/webapps",
    "removable": false,
    "name": "Music",
    "csp": "",
    "installerAppId": 0,
    "installerIsBrowser": false
  },
  "marketplace-staging": {
    "origin": "https://marketplace.allizom.org/telefonica/",
    "installOrigin": "https://marketplace.allizom.org/telefonica/",
    "receipt": null,
    "installTime": 132333986000,
    "manifestURL": "https://marketplace.allizom.org/telefonica/manifest.webapp",
    "localId": 1022,
    "etag": null,
    "packageEtag": null,
    "basePath": "/system/b2g/webapps",
    "removable": false,
    "name": "Staging Marketplace",
    "csp": "",
    "appStatus": 1,
    "installerAppId": 0,
    "installerIsBrowser": false
  },
  "maps": {
    "origin": "http://m.here.net/",
    "installOrigin": "http://m.here.net/",
    "receipt": null,
    "installTime": 132333986000,
    "manifestURL": "http://m.here.net/manifest.webapp",
    "localId": 1023,
    "etag": null,
    "packageEtag": null,
    "basePath": "/system/b2g/webapps",
    "removable": false,
    "name": "Maps",
    "csp": "",
    "appStatus": 1,
    "installerAppId": 0,
    "installerIsBrowser": false
  },
  "marketplace-dev": {
    "origin": "https://marketplace-dev.allizom.org/telefonica/",
    "installOrigin": "https://marketplace-dev.allizom.org/telefonica/",
    "receipt": null,
    "installTime": 132333986000,
    "manifestURL": "https://marketplace-dev.allizom.org/telefonica/manifest.webapp",
    "localId": 1024,
    "etag": null,
    "packageEtag": null,
    "basePath": "/system/b2g/webapps",
    "removable": false,
    "name": "Dev Marketplace",
    "csp": "",
    "appStatus": 1,
    "installerAppId": 0,
    "installerIsBrowser": false
  },
  "marketplace": {
    "origin": "https://marketplace.firefox.com/telefonica/",
    "installOrigin": "https://marketplace.firefox.com/telefonica/",
    "receipt": null,
    "installTime": 132333986000,
    "manifestURL": "https://marketplace.firefox.com/telefonica/manifest.webapp",
    "localId": 1025,
    "etag": null,
    "packageEtag": null,
    "basePath": "/system/b2g/webapps",
    "removable": false,
    "name": "Marketplace",
    "csp": "",
    "appStatus": 1,
    "installerAppId": 0,
    "installerIsBrowser": false
  }
}
